Workbook

Sheet Check
D2: Real Time TB | F2: =MATCH(E6,'Real Time TB'!$A$6:$F$6,0) -> 4 | H2: =MATCH(G6,'Real Time TB'!$A$6:$F$6,0) -> 5 | J2: =MATCH(I6,'Real Time TB'!$A$6:$F$6,0) -> 6
D3: Aggregate Exp | F3: =MATCH(E6,'Aggregate Exp'!$A$7:$E$7,0) -> 3 | H3: =MATCH(G6,'Aggregate Exp'!$A$7:$E$7,0) -> 4 | J3: =MATCH(I6,'Aggregate Exp'!$A$7:$E$7,0) -> 5 | Q3: =VLOOKUP(P8,'MA rates'!$C$2:$E$9,3,FALSE) -> 118.54 | S3: =VLOOKUP(R8,'MA rates'!$C$2:$E$9,3,FALSE) -> 107.82 | U3: =VLOOKUP(T8,'MA rates'!$C$2:$E$9,3,FALSE) -> 14.22
D4: Sum of Differences | F4: =SUM(F9:F29) -> 0 | H4: =SUM(H9:H29) -> 0.51 | J4: =SUM(J9:J29) -> 0.65 | Q4: =SUM(Q9:Q34) -> 5.5879354e-09 | S4: =SUM(S9:S34) -> -2.3574103e-09 | U4: =SUM(U9:U34) -> -6.8102963e-09 | AJ4: =SUM(AJ9:AJ34) -> 5.5879354e-09 | AL4: =SUM(AL9:AL34) -> 0 | AN4: =SUM(AN9:AN34) -> 0
E5: LC - Balance | G5: LC - Balance | I5: LC - Balance | K5: LC - Balance | L5: LC - Consol | M5: LC - Consol | N5: LC - Consol | O5: LC - Consol | P5: GC - Balance | R5: GC - Balance | T5: GC - Balance | V5: GC - Balance | W5: GC - Reclass | X5: GC - Reclass | Y5: GC - Reclass | Z5: GC - Reclass | AA5: GC - Elimination | AB5: GC - Elimination | AC5: GC - Elimination | AD5: GC - Elimination | AE5: GC - Consol | AF5: GC - Consol | AG5: GC - Consol | AH5: GC - Consol | AI5: GC - Total | AK5: GC - Total | AM5: GC - Total | AO5: GC - Total
E6: BALSCH | G6: BALSDE | I6: BALSDK | K6: Overall Result | L6: BALSCH | M6: BALSDE | N6: BALSDK | O6: Overall Result | P6: BALSCH | R6: BALSDE | T6: BALSDK | V6: Overall Result | W6: BALSCH | X6: BALSDE | Y6: BALSDK | Z6: Overall Result | AA6: BALSCH | AB6: BALSDE | AC6: BALSDK | AD6: Overall Result | AE6: BALSCH | AF6: BALSDE | AG6: BALSDK | AH6: Overall Result | AI6: BALSCH | AK6: BALSDE | AM6: BALSDK | AO6: Overall Result
E7: Base life science AG | G7: Base life science GmbH | I7: Base life science A/S | L7: Base life science AG | M7: Base life science GmbH | N7: Base life science A/S | P7: Base life science AG | R7: Base life science GmbH | T7: Base life science A/S | W7: Base life science AG | X7: Base life science GmbH | Y7: Base life science A/S | AA7: Base life science AG | AB7: Base life science GmbH | AC7: Base life science A/S | AE7: Base life science AG | AF7: Base life science GmbH | AG7: Base life science A/S | AI7: Base life science AG | AK7: Base life science GmbH | AM7: Base life science A/S
C8: GLACCOUNT | D8: GL Description | Currency | E8: CHF | G8: EUR | I8: DKK | L8: CHF | M8: EUR | N8: DKK | P8: CHF | R8: EUR | T8: DKK | W8: CHF | X8: EUR | Y8: DKK | AA8: CHF | AB8: EUR | AC8: DKK | AE8: CHF | AF8: EUR | AG8: DKK | AI8: CHF | AK8: EUR | AM8: DKK
A9: Income | B9: Revenue | C9: 311025 | D9: Overseas - Others | E9: -355672.13 | F9: =IFERROR(VLOOKUP($C9,'Real Time TB'!$A$6:$F$22,Check!F$2,FALSE),0)-E9 -> 0 | G9: -91166 | H9: =IFERROR(VLOOKUP($C9,'Real Time TB'!$A$6:$F$22,Check!H$2,FALSE),0)-G9 -> 0 | I9: -13439775 | J9: =IFERROR(VLOOKUP($C9,'Real Time TB'!$A$6:$F$22,Check!J$2,FALSE),0)-I9 -> 0 | K9: -13886613 | L9: 0 | M9: 0 | N9: 0 | O9: 0 | P9: -42161374 | Q9: =SUMIF($A$6:$N$6,P$6,$A9:$N9)*Q$3-P9 -> -0.00020000339 | R9: -9829518.1 | S9: =SUMIF($A$6:$N$6,R$6,$A9:$N9)*S$3-R9 -> 0 | T9: -1.911136e+08 | U9: =SUMIF($A$6:$N$6,T$6,$A9:$N9)*U$3-T9 -> -0.0040000081 | V9: -2.4310449e+08 | W9: 0 | X9: 0 | Y9: 0 | Z9: 0 | AA9: 0 | AB9: 0 | AC9: 0 | AD9: 0 | AE9: 0 | AF9: 0 | AG9: 0 | AH9: 0 | AI9: -42161374 | AJ9: =SUMIF($P$6:$AG$6,AI$6,$P9:$AG9)-AI9 -> 0 | AK9: -9829518.1 | AL9: =SUMIF($P$6:$AG$6,AK$6,$P9:$AG9)-AK9 -> 0 | AM9: -1.911136e+08 | AN9: =SUMIF($P$6:$AG$6,AM$6,$P9:$AG9)-AM9 -> 0 | AO9: -2.4310449e+08
A10: Income | B10: Revenue | C10: 311030 | D10: Overseas Inter company transfer | E10: -130023 | F10: =IFERROR(VLOOKUP($C10,'Real Time TB'!$A$6:$F$22,Check!F$2,FALSE),0)-E10 -> 0 | G10: -74412 | H10: =IFERROR(VLOOKUP($C10,'Real Time TB'!$A$6:$F$22,Check!H$2,FALSE),0)-G10 -> 0 | I10: -7052462.5 | J10: =IFERROR(VLOOKUP($C10,'Real Time TB'!$A$6:$F$22,Check!J$2,FALSE),0)-I10 -> 0 | K10: -7256897.5 | L10: 0 | M10: 0 | N10: 0 | O10: 0 | P10: -15412926 | Q10: =SUMIF($A$6:$N$6,P$6,$A10:$N10)*Q$3-P10 -> 0 | R10: -8023101.8 | S10: =SUMIF($A$6:$N$6,R$6,$A10:$N10)*S$3-R10 -> 0 | T10: -1.0028602e+08 | U10: =SUMIF($A$6:$N$6,T$6,$A10:$N10)*U$3-T10 -> 0 | V10: -1.2372205e+08 | W10: 0 | X10: 0 | Y10: 0 | Z10: 0 | AA10: 15412926 | AB10: 8023101.8 | AC10: 1.0028602e+08 | AD10: 1.2372205e+08 | AE10: 0 | AF10: 0 | AG10: 0 | AH10: 0 | AI10: 0 | AJ10: =SUMIF($P$6:$AG$6,AI$6,$P10:$AG10)-AI10 -> 0 | AK10: 0 | AL10: =SUMIF($P$6:$AG$6,AK$6,$P10:$AG10)-AK10 -> 0 | AM10: 0 | AN10: =SUMIF($P$6:$AG$6,AM$6,$P10:$AG10)-AM10 -> 0 | AO10: 0
B11: Revenue | E11: -485695.13 | G11: -165578 | I11: -20492237 | K11: -21143510 | L11: 0 | M11: 0 | N11: 0 | O11: 0 | P11: -57574301 | Q11: =SUMIF($A$6:$N$6,P$6,$A11:$N11)*Q$3-P11 -> -0.00020000339 | R11: -17852620 | S11: =SUMIF($A$6:$N$6,R$6,$A11:$N11)*S$3-R11 -> 0 | T11: -2.9139961e+08 | U11: =SUMIF($A$6:$N$6,T$6,$A11:$N11)*U$3-T11 -> -0.0040000081 | V11: -3.6682653e+08 | W11: 0 | X11: 0 | Y11: 0 | Z11: 0 | AA11: 15412926 | AB11: 8023101.8 | AC11: 1.0028602e+08 | AD11: 1.2372205e+08 | AE11: 0 | AF11: 0 | AG11: 0 | AH11: 0 | AI11: -42161374 | AJ11: =SUMIF($P$6:$AG$6,AI$6,$P11:$AG11)-AI11 -> 0 | AK11: -9829518.1 | AL11: =SUMIF($P$6:$AG$6,AK$6,$P11:$AG11)-AK11 -> 0 | AM11: -1.911136e+08 | AN11: =SUMIF($P$6:$AG$6,AM$6,$P11:$AG11)-AM11 -> 0 | AO11: -2.4310449e+08
A12: Expense | B12: Cost of Production | C12: 110200 | D12: Overseas Salaries excluding Medical Insurance | E12: 266422.58 | F12: =IFERROR(VLOOKUP($C12,'Aggregate Exp'!$A$7:$E$12,Check!F$3,FALSE),0)-E12 -> 0 | G12: 118158.4 | H12: =IFERROR(VLOOKUP($C12,'Aggregate Exp'!$A$7:$E$12,Check!H$3,FALSE),0)-G12 -> 0 | I12: 6290519.8 | J12: =IFERROR(VLOOKUP($C12,'Aggregate Exp'!$A$7:$E$12,Check!J$3,FALSE),0)-I12 -> 0 | K12: 6675100.8 | L12: 0 | M12: 0 | N12: 0 | O12: 0 | P12: 31581733 | Q12: =SUMIF($A$6:$N$6,P$6,$A12:$N12)*Q$3-P12 -> 0.0032000057 | R12: 12739839 | S12: =SUMIF($A$6:$N$6,R$6,$A12:$N12)*S$3-R12 -> -0.0020000003 | T12: 89451192 | U12: =SUMIF($A$6:$N$6,T$6,$A12:$N12)*U$3-T12 -> 0.0047999918 | V12: 1.3377276e+08 | W12: 0 | X12: 0 | Y12: 0 | Z12: 0 | AA12: 0 | AB12: 0 | AC12: 0 | AD12: 0 | AE12: 0 | AF12: 0 | AG12: 0 | AH12: 0 | AI12: 31581733 | AJ12: =SUMIF($P$6:$AG$6,AI$6,$P12:$AG12)-AI12 -> 0 | AK12: 12739839 | AL12: =SUMIF($P$6:$AG$6,AK$6,$P12:$AG12)-AK12 -> 0 | AM12: 89451192 | AN12: =SUMIF($P$6:$AG$6,AM$6,$P12:$AG12)-AM12 -> 0 | AO12: 1.3377276e+08
A13: Expense | B13: Cost of Production | C13: 290100 | D13: Depreciation | E13: 0 | F13: =IFERROR(VLOOKUP($C13,'Aggregate Exp'!$A$7:$E$12,Check!F$3,FALSE),0)-E13 -> 0 | G13: 0 | H13: =IFERROR(VLOOKUP($C13,'Aggregate Exp'!$A$7:$E$12,Check!H$3,FALSE),0)-G13 -> 0 | I13: 0 | J13: =IFERROR(VLOOKUP($C13,'Aggregate Exp'!$A$7:$E$12,Check!J$3,FALSE),0)-I13 -> 0 | K13: 0 | L13: 0 | M13: 0 | N13: 0 | O13: 0 | P13: 0 | Q13: =SUMIF($A$6:$N$6,P$6,$A13:$N13)*Q$3-P13 -> 0 | R13: 0 | S13: =SUMIF($A$6:$N$6,R$6,$A13:$N13)*S$3-R13 -> 0 | T13: 0 | U13: =SUMIF($A$6:$N$6,T$6,$A13:$N13)*U$3-T13 -> 0 | V13: 0 | W13: 603487.14 | X13: 49436.55 | Y13: 2238009.7 | Z13: 2890933.4 | AA13: 0 | AB13: 0 | AC13: 0 | AD13: 0 | AE13: 0 | AF13: 0 | AG13: 0 | AH13: 0 | AI13: 603487.14 | AJ13: =SUMIF($P$6:$AG$6,AI$6,$P13:$AG13)-AI13 -> 0 | AK13: 49436.55 | AL13: =SUMIF($P$6:$AG$6,AK$6,$P13:$AG13)-AK13 -> 0 | AM13: 2238009.7 | AN13: =SUMIF($P$6:$AG$6,AM$6,$P13:$AG13)-AM13 -> 0 | AO13: 2890933.4
B14: Cost of Production | E14: 266422.58 | G14: 118158.4 | I14: 6290519.8 | K14: 6675100.8 | L14: 0 | M14: 0 | N14: 0 | O14: 0 | P14: 31581733 | Q14: =SUMIF($A$6:$N$6,P$6,$A14:$N14)*Q$3-P14 -> 0.0032000057 | R14: 12739839 | S14: =SUMIF($A$6:$N$6,R$6,$A14:$N14)*S$3-R14 -> -0.0020000003 | T14: 89451192 | U14: =SUMIF($A$6:$N$6,T$6,$A14:$N14)*U$3-T14 -> 0.0047999918 | V14: 1.3377276e+08 | W14: 603487.14 | X14: 49436.55 | Y14: 2238009.7 | Z14: 2890933.4 | AA14: 0 | AB14: 0 | AC14: 0 | AD14: 0 | AE14: 0 | AF14: 0 | AG14: 0 | AH14: 0 | AI14: 32185220 | AJ14: =SUMIF($P$6:$AG$6,AI$6,$P14:$AG14)-AI14 -> 0 | AK14: 12789275 | AL14: =SUMIF($P$6:$AG$6,AK$6,$P14:$AG14)-AK14 -> 0 | AM14: 91689202 | AN14: =SUMIF($P$6:$AG$6,AM$6,$P14:$AG14)-AM14 -> 0 | AO14: 1.366637e+08
A15: Expense | B15: Sales | C15: 110200 | D15: Overseas Salaries excluding Medical Insurance | E15: 48486.19 | F15: =IFERROR(VLOOKUP($C15,'Aggregate Exp'!$G$7:$L$12,Check!F$3,FALSE),0)-E15 -> 0 | G15: 16219.93 | H15: =IFERROR(VLOOKUP($C15,'Aggregate Exp'!$G$7:$L$12,Check!H$3,FALSE),0)-G15 -> 0 | I15: 522188.52 | J15: =IFERROR(VLOOKUP($C15,'Aggregate Exp'!$G$7:$L$12,Check!J$3,FALSE),0)-I15 -> 0 | K15: 586894.64 | L15: 0 | M15: 0 | N15: 0 | O15: 0 | P15: 5747553 | Q15: =SUMIF($A$6:$N$6,P$6,$A15:$N15)*Q$3-P15 -> 0.0026000002 | R15: 1748832.9 | S15: =SUMIF($A$6:$N$6,R$6,$A15:$N15)*S$3-R15 -> 0.0025999998 | T15: 7425520.8 | U15: =SUMIF($A$6:$N$6,T$6,$A15:$N15)*U$3-T15 -> 0.0044000009 | V15: 14921907 | W15: 0 | X15: 0 | Y15: 0 | Z15: 0 | AA15: 0 | AB15: 0 | AC15: 0 | AD15: 0 | AE15: 0 | AF15: 0 | AG15: 0 | AH15: 0 | AI15: 5747553 | AJ15: =SUMIF($P$6:$AG$6,AI$6,$P15:$AG15)-AI15 -> 0 | AK15: 1748832.9 | AL15: =SUMIF($P$6:$AG$6,AK$6,$P15:$AG15)-AK15 -> 0 | AM15: 7425520.8 | AN15: =SUMIF($P$6:$AG$6,AM$6,$P15:$AG15)-AM15 -> 0 | AO15: 14921907
A16: Expense | B16: Sales | C16: 212300 | D16: Marketing expenses | E16: 0 | F16: =IFERROR(VLOOKUP($C16,'Aggregate Exp'!$G$7:$L$12,Check!F$3,FALSE),0)-E16 -> 0 | G16: 0 | H16: =IFERROR(VLOOKUP($C16,'Aggregate Exp'!$G$7:$L$12,Check!H$3,FALSE),0)-G16 -> 0 | I16: 356515.24 | J16: =IFERROR(VLOOKUP($C16,'Aggregate Exp'!$G$7:$L$12,Check!J$3,FALSE),0)-I16 -> 0 | K16: 356515.24 | L16: 0 | M16: 0 | N16: 0 | O16: 0 | P16: 0 | Q16: =SUMIF($A$6:$N$6,P$6,$A16:$N16)*Q$3-P16 -> 0 | R16: 0 | S16: =SUMIF($A$6:$N$6,R$6,$A16:$N16)*S$3-R16 -> 0 | T16: 5069646.7 | U16: =SUMIF($A$6:$N$6,T$6,$A16:$N16)*U$3-T16 -> 0.0027999999 | V16: 5069646.7 | W16: 0 | X16: 0 | Y16: 0 | Z16: 0 | AA16: 0 | AB16: 0 | AC16: 0 | AD16: 0 | AE16: 0 | AF16: 0 | AG16: 0 | AH16: 0 | AI16: 0 | AJ16: =SUMIF($P$6:$AG$6,AI$6,$P16:$AG16)-AI16 -> 0 | AK16: 0 | AL16: =SUMIF($P$6:$AG$6,AK$6,$P16:$AG16)-AK16 -> 0 | AM16: 5069646.7 | AN16: =SUMIF($P$6:$AG$6,AM$6,$P16:$AG16)-AM16 -> 0 | AO16: 5069646.7
A17: Expense | B17: Sales | C17: 212400 | D17: Sales promotion expenses | E17: 0 | F17: =IFERROR(VLOOKUP($C17,'Aggregate Exp'!$G$7:$L$12,Check!F$3,FALSE),0)-E17 -> 0 | G17: 0 | H17: =IFERROR(VLOOKUP($C17,'Aggregate Exp'!$G$7:$L$12,Check!H$3,FALSE),0)-G17 -> 0 | I17: 107043.23 | J17: =IFERROR(VLOOKUP($C17,'Aggregate Exp'!$G$7:$L$12,Check!J$3,FALSE),0)-I17 -> 0 | K17: 107043.23 | L17: 0 | M17: 0 | N17: 0 | O17: 0 | P17: 0 | Q17: =SUMIF($A$6:$N$6,P$6,$A17:$N17)*Q$3-P17 -> 0 | R17: 0 | S17: =SUMIF($A$6:$N$6,R$6,$A17:$N17)*S$3-R17 -> 0 | T17: 1522154.7 | U17: =SUMIF($A$6:$N$6,T$6,$A17:$N17)*U$3-T17 -> 0.00060000014 | V17: 1522154.7 | W17: 0 | X17: 0 | Y17: 0 | Z17: 0 | AA17: 0 | AB17: 0 | AC17: 0 | AD17: 0 | AE17: 0 | AF17: 0 | AG17: 0 | AH17: 0 | AI17: 0 | AJ17: =SUMIF($P$6:$AG$6,AI$6,$P17:$AG17)-AI17 -> 0 | AK17: 0 | AL17: =SUMIF($P$6:$AG$6,AK$6,$P17:$AG17)-AK17 -> 0 | AM17: 1522154.7 | AN17: =SUMIF($P$6:$AG$6,AM$6,$P17:$AG17)-AM17 -> 0 | AO17: 1522154.7
B18: Sales | E18: 48486.19 | G18: 16219.93 | I18: 985746.99 | K18: 1050453.1 | L18: 0 | M18: 0 | N18: 0 | O18: 0 | P18: 5747553 | Q18: =SUMIF($A$6:$N$6,P$6,$A18:$N18)*Q$3-P18 -> 0.0026000002 | R18: 1748832.9 | S18: =SUMIF($A$6:$N$6,R$6,$A18:$N18)*S$3-R18 -> 0.0025999998 | T18: 14017322 | U18: =SUMIF($A$6:$N$6,T$6,$A18:$N18)*U$3-T18 -> 0.0077999998 | V18: 21513708 | W18: 0 | X18: 0 | Y18: 0 | Z18: 0 | AA18: 0 | AB18: 0 | AC18: 0 | AD18: 0 | AE18: 0 | AF18: 0 | AG18: 0 | AH18: 0 | AI18: 5747553 | AJ18: =SUMIF($P$6:$AG$6,AI$6,$P18:$AG18)-AI18 -> 0 | AK18: 1748832.9 | AL18: =SUMIF($P$6:$AG$6,AK$6,$P18:$AG18)-AK18 -> 0 | AM18: 14017322 | AN18: =SUMIF($P$6:$AG$6,AM$6,$P18:$AG18)-AM18 -> 0 | AO18: 21513708
A19: Expense | B19: General Administration | C19: 110200 | D19: Overseas Salaries excluding Medical Insurance | E19: 23503.96 | F19: =IFERROR(VLOOKUP($C19,'Aggregate Exp'!$M$7:$R$12,Check!F$3,FALSE),0)-E19 -> 0 | G19: 0 | H19: =IFERROR(VLOOKUP($C19,'Aggregate Exp'!$M$7:$R$12,Check!H$3,FALSE),0)-G19 -> 0 | I19: 943849.52 | J19: =IFERROR(VLOOKUP($C19,'Aggregate Exp'!$M$7:$R$12,Check!J$3,FALSE),0)-I19 -> 0 | K19: 967353.48 | L19: 0 | M19: 0 | N19: 0 | O19: 0 | P19: 2786159.4 | Q19: =SUMIF($A$6:$N$6,P$6,$A19:$N19)*Q$3-P19 -> -0.0016000001 | R19: 0 | S19: =SUMIF($A$6:$N$6,R$6,$A19:$N19)*S$3-R19 -> 0 | T19: 13421540 | U19: =SUMIF($A$6:$N$6,T$6,$A19:$N19)*U$3-T19 -> 0.0044000018 | V19: 16207700 | W19: 0 | X19: 0 | Y19: 0 | Z19: 0 | AA19: 0 | AB19: 0 | AC19: 0 | AD19: 0 | AE19: 0 | AF19: 0 | AG19: 0 | AH19: 0 | AI19: 2786159.4 | AJ19: =SUMIF($P$6:$AG$6,AI$6,$P19:$AG19)-AI19 -> 0 | AK19: 0 | AL19: =SUMIF($P$6:$AG$6,AK$6,$P19:$AG19)-AK19 -> 0 | AM19: 13421540 | AN19: =SUMIF($P$6:$AG$6,AM$6,$P19:$AG19)-AM19 -> 0 | AO19: 16207700
A20: Expense | B20: General Administration | C20: 290100 | D20: Depreciation | E20: 5091 | F20: =IFERROR(VLOOKUP($C20,'Aggregate Exp'!$M$7:$R$12,Check!F$3,FALSE),0)-E20 -> 0 | G20: 458 | H20: =IFERROR(VLOOKUP($C20,'Aggregate Exp'!$M$7:$R$12,Check!H$3,FALSE),0)-G20 -> 0.51 | I20: 157384 | J20: =IFERROR(VLOOKUP($C20,'Aggregate Exp'!$M$7:$R$12,Check!J$3,FALSE),0)-I20 -> 0.65 | K20: 162933 | L20: 0 | M20: 0 | N20: 0 | O20: 0 | P20: 603487.14 | Q20: =SUMIF($A$6:$N$6,P$6,$A20:$N20)*Q$3-P20 -> 0 | R20: 49436.55 | S20: =SUMIF($A$6:$N$6,R$6,$A20:$N20)*S$3-R20 -> -54.99 | T20: 2238009.7 | U20: =SUMIF($A$6:$N$6,T$6,$A20:$N20)*U$3-T20 -> -9.24 | V20: 2890933.4 | W20: -603487.14 | X20: -49436.55 | Y20: -2238009.7 | Z20: -2890933.4 | AA20: 0 | AB20: 0 | AC20: 0 | AD20: 0 | AE20: 0 | AF20: 0 | AG20: 0 | AH20: 0 | AI20: 0 | AJ20: =SUMIF($P$6:$AG$6,AI$6,$P20:$AG20)-AI20 -> 0 | AK20: 0 | AL20: =SUMIF($P$6:$AG$6,AK$6,$P20:$AG20)-AK20 -> 0 | AM20: 0 | AN20: =SUMIF($P$6:$AG$6,AM$6,$P20:$AG20)-AM20 -> 0 | AO20: 0
B21: General Administration | E21: 28594.96 | G21: 458 | I21: 1101233.5 | K21: 1130286.5 | L21: 0 | M21: 0 | N21: 0 | O21: 0 | P21: 3389646.6 | Q21: =SUMIF($A$6:$N$6,P$6,$A21:$N21)*Q$3-P21 -> -0.0016000001 | R21: 49436.55 | S21: =SUMIF($A$6:$N$6,R$6,$A21:$N21)*S$3-R21 -> -54.99 | T21: 15659550 | U21: =SUMIF($A$6:$N$6,T$6,$A21:$N21)*U$3-T21 -> -9.2356 | V21: 19098633 | W21: -603487.14 | X21: -49436.55 | Y21: -2238009.7 | Z21: -2890933.4 | AA21: 0 | AB21: 0 | AC21: 0 | AD21: 0 | AE21: 0 | AF21: 0 | AG21: 0 | AH21: 0 | AI21: 2786159.4 | AJ21: =SUMIF($P$6:$AG$6,AI$6,$P21:$AG21)-AI21 -> 0 | AK21: 0 | AL21: =SUMIF($P$6:$AG$6,AK$6,$P21:$AG21)-AK21 -> 0 | AM21: 13421540 | AN21: =SUMIF($P$6:$AG$6,AM$6,$P21:$AG21)-AM21 -> 0 | AO21: 16207700
A22: Income | B22: Other Income | C22: 331001 | D22: Interest received on Bank A/c | E22: 0 | F22: =IFERROR(VLOOKUP($C22,'Real Time TB'!$A$6:$F$22,Check!F$2,FALSE),0)-E22 -> 0 | G22: 0 | H22: =IFERROR(VLOOKUP($C22,'Real Time TB'!$A$6:$F$22,Check!H$2,FALSE),0)-G22 -> 0 | I22: -14548.69 | J22: =IFERROR(VLOOKUP($C22,'Real Time TB'!$A$6:$F$22,Check!J$2,FALSE),0)-I22 -> 0 | K22: -14548.69 | L22: 0 | M22: 0 | N22: 0 | O22: 0 | P22: 0 | Q22: =SUMIF($A$6:$N$6,P$6,$A22:$N22)*Q$3-P22 -> 0 | R22: 0 | S22: =SUMIF($A$6:$N$6,R$6,$A22:$N22)*S$3-R22 -> 0 | T22: -206882.37 | U22: =SUMIF($A$6:$N$6,T$6,$A22:$N22)*U$3-T22 -> -0.0018 | V22: -206882.37 | W22: 0 | X22: 0 | Y22: 0 | Z22: 0 | AA22: 0 | AB22: 0 | AC22: 0 | AD22: 0 | AE22: 0 | AF22: 0 | AG22: 0 | AH22: 0 | AI22: 0 | AJ22: =SUMIF($P$6:$AG$6,AI$6,$P22:$AG22)-AI22 -> 0 | AK22: 0 | AL22: =SUMIF($P$6:$AG$6,AK$6,$P22:$AG22)-AK22 -> 0 | AM22: -206882.37 | AN22: =SUMIF($P$6:$AG$6,AM$6,$P22:$AG22)-AM22 -> 0 | AO22: -206882.37
A23: Income | B23: Other Income | C23: 334000 | D23: Translation diff | E23: 8095.75 | F23: =IFERROR(VLOOKUP($C23,'Real Time TB'!$A$6:$F$22,Check!F$2,FALSE),0)-E23 -> 0 | G23: 0 | H23: =IFERROR(VLOOKUP($C23,'Real Time TB'!$A$6:$F$22,Check!H$2,FALSE),0)-G23 -> 0 | I23: -120129.67 | J23: =IFERROR(VLOOKUP($C23,'Real Time TB'!$A$6:$F$22,Check!J$2,FALSE),0)-I23 -> 0 | K23: -112033.92 | L23: 0 | M23: 0 | N23: 0 | O23: 0 | P23: 959670.21 | Q23: =SUMIF($A$6:$N$6,P$6,$A23:$N23)*Q$3-P23 -> -0.0049999999 | R23: 0 | S23: =SUMIF($A$6:$N$6,R$6,$A23:$N23)*S$3-R23 -> 0 | T23: -1708243.9 | U23: =SUMIF($A$6:$N$6,T$6,$A23:$N23)*U$3-T23 -> 0.0025999998 | V23: -748573.7 | W23: 0 | X23: 0 | Y23: 0 | Z23: 0 | AA23: 0 | AB23: 0 | AC23: 0 | AD23: 0 | AE23: 0 | AF23: 0 | AG23: 0 | AH23: 0 | AI23: 959670.21 | AJ23: =SUMIF($P$6:$AG$6,AI$6,$P23:$AG23)-AI23 -> 0 | AK23: 0 | AL23: =SUMIF($P$6:$AG$6,AK$6,$P23:$AG23)-AK23 -> 0 | AM23: -1708243.9 | AN23: =SUMIF($P$6:$AG$6,AM$6,$P23:$AG23)-AM23 -> 0 | AO23: -748573.7
B24: Other Income | E24: 8095.75 | G24: 0 | I24: -134678.36 | K24: -126582.61 | L24: 0 | M24: 0 | N24: 0 | O24: 0 | P24: 959670.21 | Q24: =SUMIF($A$6:$N$6,P$6,$A24:$N24)*Q$3-P24 -> -0.0049999999 | R24: 0 | S24: =SUMIF($A$6:$N$6,R$6,$A24:$N24)*S$3-R24 -> 0 | T24: -1915126.3 | U24: =SUMIF($A$6:$N$6,T$6,$A24:$N24)*U$3-T24 -> 0.00079999981 | V24: -955456.07 | W24: 0 | X24: 0 | Y24: 0 | Z24: 0 | AA24: 0 | AB24: 0 | AC24: 0 | AD24: 0 | AE24: 0 | AF24: 0 | AG24: 0 | AH24: 0 | AI24: 959670.21 | AJ24: =SUMIF($P$6:$AG$6,AI$6,$P24:$AG24)-AI24 -> 0 | AK24: 0 | AL24: =SUMIF($P$6:$AG$6,AK$6,$P24:$AG24)-AK24 -> 0 | AM24: -1915126.3 | AN24: =SUMIF($P$6:$AG$6,AM$6,$P24:$AG24)-AM24 -> 0 | AO24: -955456.07
A25: Expense | B25: Provision for Tax | C25: 290900 | D25: Provision for Deferred taxes-overseas | E25: 0 | F25: =IFERROR(VLOOKUP($C25,'Real Time TB'!$A$6:$F$22,Check!F$2,FALSE),0)-E25 -> 0 | G25: 0 | H25: =IFERROR(VLOOKUP($C25,'Real Time TB'!$A$6:$F$22,Check!H$2,FALSE),0)-G25 -> 0 | I25: 0 | J25: =IFERROR(VLOOKUP($C25,'Real Time TB'!$A$6:$F$22,Check!J$2,FALSE),0)-I25 -> 0 | K25: 0 | L25: 0 | M25: 0 | N25: -677977.23 | O25: -677977.23 | P25: 0 | Q25: =SUMIF($A$6:$N$6,P$6,$A25:$N25)*Q$3-P25 -> 0 | R25: 0 | S25: =SUMIF($A$6:$N$6,R$6,$A25:$N25)*S$3-R25 -> 0 | T25: -9640836.2 | U25: =SUMIF($A$6:$N$6,T$6,$A25:$N25)*U$3-T25 -> -0.00059999898 | V25: -9640836.2 | W25: 0 | X25: 0 | Y25: 0 | Z25: 0 | AA25: 0 | AB25: 0 | AC25: 0 | AD25: 0 | AE25: 0 | AF25: 0 | AG25: 0 | AH25: 0 | AI25: 0 | AJ25: =SUMIF($P$6:$AG$6,AI$6,$P25:$AG25)-AI25 -> 0 | AK25: 0 | AL25: =SUMIF($P$6:$AG$6,AK$6,$P25:$AG25)-AK25 -> 0 | AM25: -9640836.2 | AN25: =SUMIF($P$6:$AG$6,AM$6,$P25:$AG25)-AM25 -> 0 | AO25: -9640836.2
B26: Provision for Tax | E26: 0 | G26: 0 | I26: 0 | K26: 0 | L26: 0 | M26: 0 | N26: -677977.23 | O26: -677977.23 | P26: 0 | Q26: =SUMIF($A$6:$N$6,P$6,$A26:$N26)*Q$3-P26 -> 0 | R26: 0 | S26: =SUMIF($A$6:$N$6,R$6,$A26:$N26)*S$3-R26 -> 0 | T26: -9640836.2 | U26: =SUMIF($A$6:$N$6,T$6,$A26:$N26)*U$3-T26 -> -0.00059999898 | V26: -9640836.2 | W26: 0 | X26: 0 | Y26: 0 | Z26: 0 | AA26: 0 | AB26: 0 | AC26: 0 | AD26: 0 | AE26: 0 | AF26: 0 | AG26: 0 | AH26: 0 | AI26: 0 | AJ26: =SUMIF($P$6:$AG$6,AI$6,$P26:$AG26)-AI26 -> 0 | AK26: 0 | AL26: =SUMIF($P$6:$AG$6,AK$6,$P26:$AG26)-AK26 -> 0 | AM26: -9640836.2 | AN26: =SUMIF($P$6:$AG$6,AM$6,$P26:$AG26)-AM26 -> 0 | AO26: -9640836.2
A27: Expense | B27: Interest | C27: 290410 | D27: Interest Expense on Loan from Subsidiary | E27: 0 | F27: =IFERROR(VLOOKUP($C27,'Real Time TB'!$A$6:$F$22,Check!F$2,FALSE),0)-E27 -> 0 | G27: 0 | H27: =IFERROR(VLOOKUP($C27,'Real Time TB'!$A$6:$F$22,Check!H$2,FALSE),0)-G27 -> 0 | I27: 87273.64 | J27: =IFERROR(VLOOKUP($C27,'Real Time TB'!$A$6:$F$22,Check!J$2,FALSE),0)-I27 -> 0 | K27: 87273.64 | L27: 0 | M27: 0 | N27: 0 | O27: 0 | P27: 0 | Q27: =SUMIF($A$6:$N$6,P$6,$A27:$N27)*Q$3-P27 -> 0 | R27: 0 | S27: =SUMIF($A$6:$N$6,R$6,$A27:$N27)*S$3-R27 -> 0 | T27: 1241031.2 | U27: =SUMIF($A$6:$N$6,T$6,$A27:$N27)*U$3-T27 -> 0.00080000004 | V27: 1241031.2 | W27: 0 | X27: 0 | Y27: 0 | Z27: 0 | AA27: 0 | AB27: 0 | AC27: -1241031.2 | AD27: -1241031.2 | AE27: 0 | AF27: 0 | AG27: 0 | AH27: 0 | AI27: 0 | AJ27: =SUMIF($P$6:$AG$6,AI$6,$P27:$AG27)-AI27 -> 0 | AK27: 0 | AL27: =SUMIF($P$6:$AG$6,AK$6,$P27:$AG27)-AK27 -> 0 | AM27: 0 | AN27: =SUMIF($P$6:$AG$6,AM$6,$P27:$AG27)-AM27 -> 0 | AO27: 0
B28: Interest | E28: 0 | G28: 0 | I28: 87273.64 | K28: 87273.64 | L28: 0 | M28: 0 | N28: 0 | O28: 0 | P28: 0 | Q28: =SUMIF($A$6:$N$6,P$6,$A28:$N28)*Q$3-P28 -> 0 | R28: 0 | S28: =SUMIF($A$6:$N$6,R$6,$A28:$N28)*S$3-R28 -> 0 | T28: 1241031.2 | U28: =SUMIF($A$6:$N$6,T$6,$A28:$N28)*U$3-T28 -> 0.00080000004 | V28: 1241031.2 | W28: 0 | X28: 0 | Y28: 0 | Z28: 0 | AA28: 0 | AB28: 0 | AC28: -1241031.2 | AD28: -1241031.2 | AE28: 0 | AF28: 0 | AG28: 0 | AH28: 0 | AI28: 0 | AJ28: =SUMIF($P$6:$AG$6,AI$6,$P28:$AG28)-AI28 -> 0 | AK28: 0 | AL28: =SUMIF($P$6:$AG$6,AK$6,$P28:$AG28)-AK28 -> 0 | AM28: 0 | AN28: =SUMIF($P$6:$AG$6,AM$6,$P28:$AG28)-AM28 -> 0 | AO28: 0
A29: Expense | B29: Provision for Investment | C29: 290510 | D29: Provision on investment - Subsidiary | E29: 0 | F29: =IFERROR(VLOOKUP($C29,'Real Time TB'!$A$6:$F$22,Check!F$2,FALSE),0)-E29 -> 0 | G29: 0 | H29: =IFERROR(VLOOKUP($C29,'Real Time TB'!$A$6:$F$22,Check!H$2,FALSE),0)-G29 -> 0 | I29: 0 | J29: =IFERROR(VLOOKUP($C29,'Real Time TB'!$A$6:$F$22,Check!J$2,FALSE),0)-I29 -> 0 | K29: 0 | L29: 0 | M29: 0 | N29: 0 | O29: 0 | P29: 0 | Q29: =SUMIF($A$6:$N$6,P$6,$A29:$N29)*Q$3-P29 -> 0 | R29: 0 | S29: =SUMIF($A$6:$N$6,R$6,$A29:$N29)*S$3-R29 -> 0 | T29: 0 | U29: =SUMIF($A$6:$N$6,T$6,$A29:$N29)*U$3-T29 -> 0 | V29: 0 | W29: 0 | X29: 0 | Y29: 0 | Z29: 0 | AA29: 0 | AB29: 0 | AC29: 0 | AD29: 0 | AE29: 0 | AF29: 0 | AG29: 0 | AH29: 0 | AI29: 0 | AJ29: =SUMIF($P$6:$AG$6,AI$6,$P29:$AG29)-AI29 -> 0 | AK29: 0 | AL29: =SUMIF($P$6:$AG$6,AK$6,$P29:$AG29)-AK29 -> 0 | AM29: 0 | AN29: =SUMIF($P$6:$AG$6,AM$6,$P29:$AG29)-AM29 -> 0 | AO29: 0
B30: Provision for Investment | E30: 0 | G30: 0 | I30: 0 | K30: 0 | L30: 0 | M30: 0 | N30: 0 | O30: 0 | P30: 0 | Q30: =SUMIF($A$6:$N$6,P$6,$A30:$N30)*Q$3-P30 -> 0 | R30: 0 | S30: =SUMIF($A$6:$N$6,R$6,$A30:$N30)*S$3-R30 -> 0 | T30: 0 | U30: =SUMIF($A$6:$N$6,T$6,$A30:$N30)*U$3-T30 -> 0 | V30: 0 | W30: 0 | X30: 0 | Y30: 0 | Z30: 0 | AA30: 0 | AB30: 0 | AC30: 0 | AD30: 0 | AE30: 0 | AF30: 0 | AG30: 0 | AH30: 0 | AI30: 0 | AJ30: =SUMIF($P$6:$AG$6,AI$6,$P30:$AG30)-AI30 -> 0 | AK30: 0 | AL30: =SUMIF($P$6:$AG$6,AK$6,$P30:$AG30)-AK30 -> 0 | AM30: 0 | AN30: =SUMIF($P$6:$AG$6,AM$6,$P30:$AG30)-AM30 -> 0 | AO30: 0
B31: Minority Interest | C31: 380900 | D31: Minority Interest | E31: 0 | G31: 0 | I31: 0 | K31: 0 | L31: 0 | M31: 0 | N31: 0 | O31: 0 | P31: 0 | Q31: =SUMIF($A$6:$N$6,P$6,$A31:$N31)*Q$3-P31 -> 0 | R31: 0 | S31: =SUMIF($A$6:$N$6,R$6,$A31:$N31)*S$3-R31 -> 0 | T31: 0 | U31: =SUMIF($A$6:$N$6,T$6,$A31:$N31)*U$3-T31 -> 0 | V31: 0 | W31: 0 | X31: 0 | Y31: 0 | Z31: 0 | AA31: 0 | AB31: 0 | AC31: 0 | AD31: 0 | AE31: 0 | AF31: 0 | AG31: 0 | AH31: 0 | AI31: 0 | AJ31: =SUMIF($P$6:$AG$6,AI$6,$P31:$AG31)-AI31 -> 0 | AK31: 0 | AL31: =SUMIF($P$6:$AG$6,AK$6,$P31:$AG31)-AK31 -> 0 | AM31: 0 | AN31: =SUMIF($P$6:$AG$6,AM$6,$P31:$AG31)-AM31 -> 0 | AO31: 0
B32: Minority Interest | E32: 0 | G32: 0 | I32: 0 | K32: 0 | L32: 0 | M32: 0 | N32: 0 | O32: 0 | P32: 0 | Q32: =SUMIF($A$6:$N$6,P$6,$A32:$N32)*Q$3-P32 -> 0 | R32: 0 | S32: =SUMIF($A$6:$N$6,R$6,$A32:$N32)*S$3-R32 -> 0 | T32: 0 | U32: =SUMIF($A$6:$N$6,T$6,$A32:$N32)*U$3-T32 -> 0 | V32: 0 | W32: 0 | X32: 0 | Y32: 0 | Z32: 0 | AA32: 0 | AB32: 0 | AC32: 0 | AD32: 0 | AE32: 0 | AF32: 0 | AG32: 0 | AH32: 0 | AI32: 0 | AJ32: =SUMIF($P$6:$AG$6,AI$6,$P32:$AG32)-AI32 -> 0 | AK32: 0 | AL32: =SUMIF($P$6:$AG$6,AK$6,$P32:$AG32)-AK32 -> 0 | AM32: 0 | AN32: =SUMIF($P$6:$AG$6,AM$6,$P32:$AG32)-AM32 -> 0 | AO32: 0
A33: Net Profit | B33: Net Profit | C33: 390000 | D33: P & L Account | E33: 134095.65 | G33: 30741.67 | I33: 12162142 | K33: 12326979 | L33: 0 | M33: 0 | N33: 677977.23 | O33: 677977.23 | P33: 15895698 | Q33: =SUMIF($A$6:$N$6,P$6,$A33:$N33)*Q$3-P33 -> 0.0010000002 | R33: 3314511.9 | S33: =SUMIF($A$6:$N$6,R$6,$A33:$N33)*S$3-R33 -> 54.9894 | T33: 1.8258648e+08 | U33: =SUMIF($A$6:$N$6,T$6,$A33:$N33)*U$3-T33 -> 9.226 | V33: 2.0179669e+08 | W33: 0 | X33: 0 | Y33: 0 | Z33: 0 | AA33: -15412926 | AB33: -8023101.8 | AC33: -99044986 | AD33: -1.2248101e+08 | AE33: 0 | AF33: 0 | AG33: 0 | AH33: 0 | AI33: =-SUM(AI24+AI21+AI11+AI14+AI18+AI26+AI28) -> 482771.93 | AJ33: =SUMIF($P$6:$AG$6,AI$6,$P33:$AG33)-AI33 -> 2.7939677e-09 | AK33: -4708590 | AL33: =SUMIF($P$6:$AG$6,AK$6,$P33:$AG33)-AK33 -> 0 | AM33: 83541495 | AN33: =SUMIF($P$6:$AG$6,AM$6,$P33:$AG33)-AM33 -> 0 | AO33: 79315676
B34: Net Profit | E34: 134095.65 | G34: 30741.67 | I34: 12162142 | K34: 12326979 | L34: 0 | M34: 0 | N34: 677977.23 | O34: 677977.23 | P34: 15895698 | Q34: =SUMIF($A$6:$N$6,P$6,$A34:$N34)*Q$3-P34 -> 0.0010000002 | R34: 3314511.9 | S34: =SUMIF($A$6:$N$6,R$6,$A34:$N34)*S$3-R34 -> 54.9894 | T34: 1.8258648e+08 | U34: =SUMIF($A$6:$N$6,T$6,$A34:$N34)*U$3-T34 -> 9.226 | V34: 2.0179669e+08 | W34: 0 | X34: 0 | Y34: 0 | Z34: 0 | AA34: -15412926 | AB34: -8023101.8 | AC34: -99044986 | AD34: -1.2248101e+08 | AE34: 0 | AF34: 0 | AG34: 0 | AH34: 0 | AI34: 482771.93 | AJ34: =SUMIF($P$6:$AG$6,AI$6,$P34:$AG34)-AI34 -> 2.7939677e-09 | AK34: -4708590 | AL34: =SUMIF($P$6:$AG$6,AK$6,$P34:$AG34)-AK34 -> 0 | AM34: 83541495 | AN34: =SUMIF($P$6:$AG$6,AM$6,$P34:$AG34)-AM34 -> 0 | AO34: 79315676
D36: Income | F36: =SUMIF($A:$A,$D36,E:E) -> -477599.38 | H36: =SUMIF($A:$A,$D36,G:G) -> -165578 | J36: =SUMIF($A:$A,$D36,I:I) -> -20626916
D37: Expense | F37: =SUMIF($A:$A,$D37,E:E) -> 343503.73 | H37: =SUMIF($A:$A,$D37,G:G) -> 134836.33 | J37: =SUMIF($A:$A,$D37,I:I) -> 8464774
D38: Net Profit | F38: =SUMIF($A:$A,$D38,E:E) -> 134095.65 | H38: =SUMIF($A:$A,$D38,G:G) -> 30741.67 | J38: =SUMIF($A:$A,$D38,I:I) -> 12162142
D40: Calc Check | F40: =F36+F37+F38 -> 0 | H40: =H36+H37+H38 -> 0 | J40: =J36+J37+J38 -> 0
D42: Net Profit as per Real Time TB | F42: =HLOOKUP(E6,'Real Time TB'!$C$6:$F$23,18,FALSE) -> -134095.65 | H42: =HLOOKUP(G6,'Real Time TB'!$C$6:$F$23,18,FALSE) -> -30741.16 | J42: =HLOOKUP(I6,'Real Time TB'!$C$6:$F$23,18,FALSE) -> -12162141
D43: Check | F43: =F38+F42 -> 0 | H43: =H38+H42 -> 0.51 | J43: =J38+J42 -> 0.65

Sheet MA rates
A1: ExRt | B1: Valid from | C1: From | D1: To | E1: Exch. Rate | F1: From Ratio
A2: MA | B2: 31.03.2026 | C2: TRY | D2: INR | E2: 2.1 | F2: 1
A3: MA | B3: 31.03.2026 | C3: CHF | D3: INR | E3: 118.54 | F3: 1
A4: MA | B4: 31.03.2026 | C4: EUR | D4: INR | E4: 107.82 | F4: 1
A5: MA | B5: 31.03.2026 | C5: HUF | D5: INR | E5: 27.96 | F5: 100
A6: MA | B6: 31.03.2026 | C6: JPY | D6: INR | E6: 58.68 | F6: 100
A7: MA | B7: 31.03.2026 | C7: DKK | D7: INR | E7: 14.22 | F7: 1
A8: MA | B8: 31.03.2026 | C8: USD | D8: INR | E8: 93.57 | F8: 1
A9: MA | B9: 31.03.2026 | C9: INR | D9: INR | E9: 1 | F9: 1

Sheet Real Time TB
A1: Trial Balance- Real time Companywise
A3: List of Exceptions
A4: No exceptions defined
B6: Company | C6: ATI10N | D6: BALSCH | E6: BALSDE | F6: BALSDK
C7: Inf Aus Tech Serv Pty Ltd | D7: Base life science AG | E7: Base life science GmbH | F7: Base life science A/S
C8: Sales for the Period | D8: Sales for the Period | E8: Sales for the Period | F8: Sales for the Period
A9: Group Account Number | C9: AUD | D9: CHF | E9: EUR | F9: DKK
A10: 110200 | B10: Overseas Salaries excluding Medical Insu | C10: 0 | D10: 338412.73 | E10: 134378.33 | F10: 7756557.9
A11: 212300 | B11: Marketing expenses | C11: 0 | D11: 0 | E11: 0 | F11: 356515.24
A12: 212400 | B12: Sales promotion expenses | C12: 0 | D12: 0 | E12: 0 | F12: 107043.23
A13: 290100 | B13: Depreciation | C13: 0 | D13: 5091 | E13: 458.51 | F13: 157384.65
A14: 290410 | B14: Interest expense on Loan from Subsidiary | C14: 0 | D14: 0 | E14: 0 | F14: 87273.64
A15: 290900 | B15: Provision for Deferred taxes - Overseas | C15: 0 | D15: 0 | E15: 0 | F15: 0
A16: 311025 | B16: Overseas - Others | C16: 0 | D16: -355672.13 | E16: -91166 | F16: -13439775
A17: 311030 | B17: Overseas Inter company transfer | C17: 0 | D17: -130023 | E17: -74412 | F17: -7052462.5
A18: 331001 | B18: Interest received on Bank acccounts A/c | C18: 0 | D18: 0 | E18: 0 | F18: -14548.69
A19: 334000 | B19: Translation differences | C19: 0 | D19: 8095.75 | E19: 0 | F19: -120129.67
A20: 445600 | B20: Assets/ Liabiities | C20: 2300 | D20: 0 | E20: 8000 | F20: 9000
A21: 885900 | B21: Assets/ Liabiities | C21: 4500 | D21: 6000 | E21: 0 | F21: 0
A22: 995600 | B22: Assets/ Liabiities | C22: 6700 | D22: 0 | E22: 0 | F22: 1000
C23: =SUM(C10:C19) -> 0 | D23: =SUM(D10:D19) -> -134095.65 | E23: =SUM(E10:E19) -> -30741.16 | F23: =SUM(F10:F19) -> -12162141

Sheet Aggregate Exp
A1: Aggregate Expenses | G1: Aggregate Expenses | M1: Aggregate Expenses
A3: List of Exceptions | G3: List of Exceptions | M3: List of Exceptions
A4: No exceptions defined | G4: No exceptions defined | M4: No exceptions defined
C6: Cost of revenue | D6: Cost of revenue | E6: Cost of revenue | F6: Cost of revenue | I6: Sales & Marketing | J6: Sales & Marketing | K6: Sales & Marketing | L6: Sales & Marketing | O6: General Administration | P6: General Administration | Q6: General Administration | R6: General Administration | S6: Total | T6: Total | U6: Total | V6: Total
B7: Company | C7: BALSCH | D7: BALSDE | E7: BALSDK | F7: Overall Result | H7: Company | I7: BALSCH | J7: BALSDE | K7: BALSDK | L7: Overall Result | N7: Company | O7: BALSCH | P7: BALSDE | Q7: BALSDK | R7: Overall Result | S7: BALSCH | T7: BALSDE | U7: BALSDK | V7: Overall Result
A8: Group Account Number | C8: Base life science AG | D8: Base life science GmbH | E8: Base life science A/S | G8: Group Account Number | I8: Base life science AG | J8: Base life science GmbH | K8: Base life science A/S | M8: Group Account Number | O8: Base life science AG | P8: Base life science GmbH | Q8: Base life science A/S | S8: Base life science AG | T8: Base life science GmbH | U8: Base life science A/S
A9: 110200 | B9: Overseas Salaries excluding Medical Insurance | C9: 266422.58 | D9: 118158.4 | E9: 6290519.8 | F9: 6675100.8 | G9: 110200 | H9: Overseas Salaries excluding Medical Insurance | I9: 48486.19 | J9: 16219.93 | K9: 522188.52 | L9: 586894.64 | M9: 110200 | N9: Overseas Salaries excluding Medical Insurance | O9: 23503.96 | P9: 0 | Q9: 943849.52 | R9: 967353.48 | S9: 338412.73 | T9: 134378.33 | U9: 7756557.9 | V9: 8229348.9
A10: 212300 | B10: Marketing expenses | C10: 0 | D10: 0 | E10: 0 | F10: 0 | G10: 212300 | H10: Marketing expenses | I10: 0 | J10: 0 | K10: 356515.24 | L10: 356515.24 | M10: 212300 | N10: Marketing expenses | O10: 0 | P10: 0 | Q10: 0 | R10: 0 | S10: 0 | T10: 0 | U10: 356515.24 | V10: 356515.24
A11: 212400 | B11: Sales promotion expenses | C11: 0 | D11: 0 | E11: 0 | F11: 0 | G11: 212400 | H11: Sales promotion expenses | I11: 0 | J11: 0 | K11: 107043.23 | L11: 107043.23 | M11: 212400 | N11: Sales promotion expenses | O11: 0 | P11: 0 | Q11: 0 | R11: 0 | S11: 0 | T11: 0 | U11: 107043.23 | V11: 107043.23
A12: 290100 | B12: Depreciation | C12: 0 | D12: 0 | E12: 0 | F12: 0 | G12: 290100 | H12: Depreciation | I12: 0 | J12: 0 | K12: 0 | L12: 0 | M12: 290100 | N12: Depreciation | O12: 5091 | P12: 458.51 | Q12: 157384.65 | R12: 162934.16 | S12: 5091 | T12: 458.51 | U12: 157384.65 | V12: 162934.16
A13: Overall Result | C13: 266422.58 | D13: 118158.4 | E13: 6290519.8 | F13: 6675100.8 | I13: 48486.19 | J13: 16219.93 | K13: 985746.99 | L13: 1050453.1 | O13: 28594.96 | P13: 458.51 | Q13: 1101234.2 | R13: 1130287.6 | S13: 343503.73 | T13: 134836.84 | U13: 8377501 | V13: 8855841.6
